language_practice/__init__.py
language_practice/cache.py
language_practice/repetition.py
language_practice/terminal.py
language_practice/toml.py
language_practice/web/__init__.py
language_practice/web/fr.py
language_practice/web/ru.py
language_practice/web/shared.py
language_practice/web/uk.py
language_practice-0.1.5.data/scripts/language-practice
language_practice-0.1.5.dist-info/LICENSE
language_practice-0.1.5.dist-info/METADATA
language_practice-0.1.5.dist-info/WHEEL
language_practice-0.1.5.dist-info/top_level.txt
language_practice-0.1.5.dist-info/RECORD
