Metadata-Version: 2.1
Name: language-practice
Version: 0.1.5
Summary: Flashcard app with support for downloading inflection tables
Home-page: https://github.com/jbaublitz/language-practice
Author: John Baublitz
Author-email: "john.m.baublitz@gmail.com"
License: BSD-3-Clause
License-File: LICENSE
Requires-Dist: aiohttp
Requires-Dist: beautifulsoup4
Requires-Dist: requests
Requires-Dist: tabulate
